kiwoom_rest_api/__init__.py
kiwoom_rest_api/api.py
kiwoom_rest_api/api_async.py
kiwoom_rest_api/auth/__init__.py
kiwoom_rest_api/auth/token.py
kiwoom_rest_api/cli/__init__.py
kiwoom_rest_api/cli/main.py
kiwoom_rest_api/config.py
kiwoom_rest_api/core/__init__.py
kiwoom_rest_api/core/async_client.py
kiwoom_rest_api/core/base.py
kiwoom_rest_api/core/base_api.py
kiwoom_rest_api/core/sync_client.py
kiwoom_rest_api/koreanstock/__init__.py
kiwoom_rest_api/koreanstock/account.py
kiwoom_rest_api/koreanstock/analysis.py
kiwoom_rest_api/koreanstock/chart.py
kiwoom_rest_api/koreanstock/credit_order.py
kiwoom_rest_api/koreanstock/elw.py
kiwoom_rest_api/koreanstock/etf.py
kiwoom_rest_api/koreanstock/foreign_institution.py
kiwoom_rest_api/koreanstock/investor.py
kiwoom_rest_api/koreanstock/market_condition.py
kiwoom_rest_api/koreanstock/order.py
kiwoom_rest_api/koreanstock/rank_info.py
kiwoom_rest_api/koreanstock/sector.py
kiwoom_rest_api/koreanstock/slb.py
kiwoom_rest_api/koreanstock/stockinfo.py
kiwoom_rest_api/koreanstock/theme.py
kiwoom_rest_api/koreanstock/trading.py
kiwoom_rest_api-0.1.12.dist-info/entry_points.txt
kiwoom_rest_api-0.1.12.dist-info/LICENSE
kiwoom_rest_api-0.1.12.dist-info/METADATA
kiwoom_rest_api-0.1.12.dist-info/WHEEL
kiwoom_rest_api-0.1.12.dist-info/RECORD
