Metadata-Version: 2.1
Name: kiwoom-rest-api
Version: 0.1.12
Summary: Kiwoom REST API client for Python
Author: bamjun
Author-email: khy5116@naver.com
Requires-Python: >=3.9,<4.0
Classifier: Programming Language :: Python :: 3
Classifier: Programming Language :: Python :: 3.9
Classifier: Programming Language :: Python :: 3.10
Classifier: Programming Language :: Python :: 3.11
Classifier: Programming Language :: Python :: 3.12
Requires-Dist: httpx (>=0.28.0,<0.29.0)
Requires-Dist: rich (>=13.0.0,<14.0.0)
Requires-Dist: typer (>=0.9.0,<0.10.0)
